NightWind3DLib/__init__.py
NightWind3DLib/galaxy.py
NightWind3DLib/window.py
NightWind3DLib/images_galaxy/planet1.egg
NightWind3DLib/images_galaxy/planet2.egg
NightWind3DLib/images_galaxy/planet3.egg
NightWind3DLib/images_galaxy/planet4.egg
NightWind3DLib/images_galaxy/planet5.egg
NightWind3DLib/images_galaxy/planet6.egg
NightWind3DLib/images_galaxy/space_sky.egg
NightWind3DLib/images_galaxy/texture/10.png
NightWind3DLib/images_galaxy/texture/12.png
NightWind3DLib/images_galaxy/texture/3.png
NightWind3DLib/images_galaxy/texture/4.png
NightWind3DLib/images_galaxy/texture/9.png
NightWind3DLib/images_galaxy/texture/XQ_1.png
NightWind3DLib/images_galaxy/texture/XQ_1_T.png
NightWind3DLib/images_galaxy/texture/XQ_1_Y.png
NightWind3DLib/images_galaxy/texture/XQ_2.png
NightWind3DLib/images_galaxy/texture/XQ_3.png
NightWind3DLib/images_galaxy/texture/XQ_4.png
NightWind3DLib/images_window/school.egg.pz
NightWind3DLib/images_window/space.egg.pz
NightWind3DLib/images_window/space_start.egg
NightWind3DLib/images_window/texture/00001.png
NightWind3DLib/images_window/texture/00071.png
NightWind3DLib/images_window/texture/Body01_col_1001.png
NightWind3DLib/images_window/texture/Body_bm_1001.png
NightWind3DLib/images_window/texture/Body_col_1001.png
NightWind3DLib/images_window/texture/Deng2_col_1001.png
NightWind3DLib/images_window/texture/Deng_ZFG_1001.png
NightWind3DLib/images_window/texture/Deng_col_1001.png
NightWind3DLib/images_window/texture/NeiBu2_col_1001.png
NightWind3DLib/images_window/texture/NeiBu_col_1001.png
NightWind3DLib/images_window/texture/damen.png
NightWind3DLib/images_window/texture/damen2.png
NightWind3DLib/images_window/texture/damen3.png
NightWind3DLib/images_window/texture/damen4.png
NightWind3DLib/images_window/texture/diaosu.psd
NightWind3DLib/images_window/texture/dimian.psd
NightWind3DLib/images_window/texture/fire (1).png
NightWind3DLib/images_window/texture/fire (2).png
NightWind3DLib/images_window/texture/huacao.png
NightWind3DLib-0.0.3.dist-info/METADATA
NightWind3DLib-0.0.3.dist-info/WHEEL
NightWind3DLib-0.0.3.dist-info/top_level.txt
NightWind3DLib-0.0.3.dist-info/RECORD
